{
  "type": "native",
  "data": {
    "node_id": "initialize_candy_guard",
    "version": "0.1",
    "display_name": "Initialize Candy Guard",
    "description": "",
    "width": 200,
    "height": 290,
    "backgroundColorDark": "#000000",
    "backgroundColor": "#fff"
  },
  "sources": [
    {
      "name": "signature",
      "type": "string",
      "defaultValue": "",
      "tooltip": ""
    },
    {
      "name": "candy_guard",
      "type": "pubkey",
      "defaultValue": "",
      "tooltip": ""
    }
  ],
  "targets": [
    {
      "name": "base",
      "type_bounds": ["keypair"],
      "required": true,
      "defaultValue": "",
      "tooltip": "",
      "passthrough": true
    },
    {
      "name": "authority",
      "type_bounds": ["pubkey"],
      "required": true,
      "defaultValue": "",
      "tooltip": "",
      "passthrough": false
    },
    {
      "name": "payer",
      "type_bounds": ["keypair"],
      "required": true,
      "defaultValue": "",
      "tooltip": "",
      "passthrough": true
    },
    {
      "name": "candy_guards",
      "type_bounds": ["json"],
      "required": false,
      "defaultValue": "",
      "tooltip": "",
      "passthrough": false
    },
    {
      "name": "submit",
      "type_bounds": ["bool"],
      "required": false,
      "defaultValue": true,
      "tooltip": "",
      "passthrough": false
    }
  ],
  "targets_form.json_schema": {},
  "targets_form.ui_schema": {}
}
